FOREX_LIB/__init__.py
FOREX_LIB/forex_lib.py
FOREX_LIB-0.1.0.dist-info/METADATA
FOREX_LIB-0.1.0.dist-info/WHEEL
FOREX_LIB-0.1.0.dist-info/top_level.txt
FOREX_LIB-0.1.0.dist-info/RECORD
